Workbook
Name rngAction: #REF!
Name rngBlockFactor: #REF!
Name rngCIName: #REF!
Name rngCINameHidden: #REF!
Name rngDataInputCIName: #REF!
Name rngErrorThreshold: #REF!
Name rngFileNameHidden: #REF!
Name rngHTTPPort: #REF!
Name rngLanguageCD: #REF!
Name rngMachineName: #REF!
Name rngNode: #REF!
Name rngPasswordHidden: #REF!
Name rngPortal: #REF!
Name rngProtocol: #REF!
Name rngPSSiteName: #REF!
Name rngResHeaders: #REF!
Name rngURL: #REF!
Name rngUserIDHidden: #REF!
Name rngXmlConst: #REF!
Name txtBoxTitleConnectInfo: "txtBoxTitle"
Name txtBoxTitleCreateTemplate: "txtBoxTitle"
Name txtBoxTitleInputData: "txtBoxTitle"
Name txtBoxTitleStageSubmitData: "txtBoxTitle"

Sheet 付款通知书
A2: 付款通知书
A3: 付款单位: | B3: 零一创造欢乐（深圳）科技有限公司
A4: 账单月 | B4: 缴纳地 | C4: 社保小计 | D4: 公积金小计 | E4: 残障金小计 | F4: 其他 | G4: 服务费 | H4: 全额税费 | I4: 合计 | J4: 备注 | K4: 合作产品
A5: 202603 | B5: 上海 | C5: =SUMIF(付款明细!F:F,B5,付款明细!AR:AR) -> 40399.2 | D5: =SUMIF(付款明细!F:F,B5,付款明细!AY:AY) -> 15540 | E5: =SUMIF(付款明细!F:F,B5,付款明细!BA:BA) -> 1502.3 | F5: =SUMIF(付款明细!F:F,B5,付款明细!BB:BB) -> 0 | G5: =SUMIF(付款明细!F:F,B5,付款明细!BI:BI) -> 360 | H5: =SUMIF(付款明细!F:F,B5,付款明细!BJ:BJ) -> 15867.183 | I5: =SUM(C5:H5) -> 73668.683 | J5: 12 | K5: 人事外包
A6: 202603 | B6: 广东广州 | C6: =SUMIF(付款明细!F:F,B6,付款明细!AR:AR) -> 1923.11 | D6: =SUMIF(付款明细!F:F,B6,付款明细!AY:AY) -> 6000 | E6: =SUMIF(付款明细!F:F,B6,付款明细!BA:BA) -> 30.59 | F6: =SUMIF(付款明细!F:F,B6,付款明细!BB:BB) -> 0 | G6: =SUMIF(付款明细!F:F,B6,付款明细!BI:BI) -> 30 | H6: =SUMIF(付款明细!F:F,B6,付款明细!BJ:BJ) -> 536.50464 | I6: =SUM(C6:H6) -> 8520.2046 | J6: 1
A7: 历史结余
A8: 合计 | C8: =ROUND(SUM(C5:C7),2) -> 42322.31 | D8: =ROUND(SUM(D5:D7),2) -> 21540 | E8: =ROUND(SUM(E5:E7),2) -> 1532.89 | F8: =ROUND(SUM(F5:F7),2) -> 0 | G8: =ROUND(SUM(G5:G7),2) -> 390 | H8: =ROUND(SUM(H5:H7),2) -> 16403.69 | I8: =ROUND(SUM(I5:I7),2) -> 82188.89 | J8: =SUM(J5:J7) -> 13
A10: 汇入公司名称：深圳市万泉河人力资源有限公司
A11: 开户行：中国银行深圳金地支行
A12: 帐 号：745857952481
A13: 社保顾问：薛小妹
A14: 联系电话：0755-33037777-885
A15: 特别说明： 1、请以零一创造欢乐（深圳）科技有限公司公账付款至我司，我司不接受其他公司代支付，亦不接受个人账户打款。 2、请在首次款项支付当月向我司顾问提供准确的开票信息，逾期不予开具发票；次月起，发票类型、发票税号、发票寄送信息等相关开票信息如有变更，请在当月款项支付前告知我司顾问。 3、开票抬头为：零一创造欢乐（深圳）科技有限公司，如有疑义请在汇款前联系我司顾问，款项支付后开票抬头无法变更。

Sheet 付款明细
A1: 序号 | B1: 状态 | C1: 客户名称 | D1: 姓名 | E1: 身份证号 | F1: 参保地 | G1: 户籍性质 | H1: 社保起做时间 | I1: 公积金起做时间 | J1: 帐单年月 | K1: 社保费用所属月（缴纳月） | L1: 公积金费用所属月（缴纳月） | M1: 养老企业基数 | N1: 养老企业比例 | O1: 养老企业汇缴 | P1: 养老个人基数 | Q1: 养老个人比例 | R1: 养老个人汇缴 | S1: 养老合计 | T1: 医疗企业基数 | U1: 医疗企业比例 | V1: 医疗企业大病 | W1: 医疗企业汇缴 | X1: 医疗个人基数 | Y1: 医疗个人比例 | Z1: 医疗个人大病 | AA1: 医疗个人汇缴 | AB1: 医疗合计 | AC1: 失业企业基数 | AD1: 失业企业比例 | AE1: 失业单位汇缴 | AF1: 失业个人基数 | AG1: 失业个人比例 | AH1: 失业个人汇缴 | AI1: 失业合计 | AJ1: 生育企业基数 | AK1: 生育企业比例 | AL1: 生育企业汇缴 | AM1: 工伤企业基数 | AN1: 工伤企业比例 | AO1: 工伤企业汇缴 | AP1: 单位社保 | AQ1: 个人社保 | AR1: 社保合计 | AS1: 公积金企业基数 | AT1: 公积金企业比例 | AU1: 公积金企业汇缴 | AV1: 公积金个人基数 | AW1: 公积金个人比例 | AX1: 公积金个人汇缴 | AY1: 公积金合计 | AZ1: 社保公积金小计 | BA1: 残保金企业缴纳 | BB1: 滞纳金 | BC1: 档案费 | BD1: 制卡费 | BE1: 工会费 | BF1: 采暖费 | BG1: 其它费用 | BH1: 小计（不含服务费） | BI1: 服务费 | BJ1: 全额税费 | BK1: 合计 | BL1: 备注 | BM1: 社保 | BN1: 社保差额 | BO1: 公积金 | BP1: 公积金差额 | BQ1: 社保编号 | BR1: 公积金编号 | BS1: 医保个账 | BT1: 住院基本医疗 | BU1: 住院补充医疗 | BV1: 门诊基本医疗 | BW1: 医保个账单位金额 | BX1: 医保个账个人金额 | BY1: 住院基本医疗单位金额 | BZ1: 住院补充医疗单位金额 | CA1: 门诊医疗单位金额 | CB1: 门诊医疗个人金额 | CC1: 补充公积金 基数 | CD1: 补充公积金 单位比例 | CE1: 补充公积金 个人比例 | CF1: 补充公积 金单位金额 | CG1: 补充公积金 个人金额
A2: =IF(OR(B2="正常",B2="新增"),MAX(A$1:$B1)+1,"") -> 1 | B2: 正常 | C2: 零一创造欢乐（深圳）科技有限公司 | D2: 张若涵 | E2: 622824199501080188 | F2: 上海 | G2: 外地城镇 | H2: 202311 | I2: 202311 | J2: 202603 | K2: =J2 -> 202603 | L2: =K2 -> 202603 | M2: 7460 | N2: 0.16 | O2: =ROUND(M2*N2,2) -> 1193.6 | P2: =M2 -> 7460 | Q2: 0.08 | R2: =ROUNDUP(P2*Q2,2) -> 596.8 | S2: =O2+R2 -> 1790.4 | T2: 7460 | U2: 0.09 | V2: 0 | W2: =ROUND(T2*U2,2)+V2+BW2+BY2+BZ2+CA2 -> 671.4 | X2: =T2 -> 7460 | Y2: 0.02 | Z2: 0 | AA2: =ROUNDUP(X2*Y2,2)+Z2+BX2+CB2 -> 149.2 | AB2: =W2+AA2 -> 820.6 | AC2: 7460 | AD2: 0.005 | AE2: =ROUND(AC2*AD2,2) -> 37.3 | AF2: =AC2 -> 7460 | AG2: 0.005 | AH2: =ROUND(AF2*AG2,2) -> 37.3 | AI2: =AE2+AH2 -> 74.6 | AJ2: 0 | AK2: 0 | AL2: =ROUND(AJ2*AK2,2) -> 0 | AM2: 7460 | AN2: 0.002 | AO2: =ROUND(AM2*AN2,2) -> 14.92 | AP2: =O2+AO2+AL2+AE2+W2 -> 1917.22 | AQ2: =R2+AH2+AA2 -> 783.3 | AR2: =AP2+AQ2 -> 2700.52 | AS2: 7384 | AT2: 0.07 | AU2: =ROUND(AS2*AT2,0)+CF2 -> 517 | AV2: =AS2 -> 7384 | AW2: =AT2 -> 0.07 | AX2: =ROUND(AV2*AW2,0)+CG2 -> 517 | AY2: =AU2+AX2 -> 1034 | AZ2: =AR2+AY2 -> 3734.52 | BA2: =ROUNDUP(M2*1.5%*90%,1) -> 100.8 | BB2: 0 | BC2: 0 | BD2: 0 | BE2: 0 | BF2: 0 | BG2: 0 | BH2: =SUM(AZ2:BG2) -> 3835.32 | BI2: 30 | BJ2: =SUM(BH2:BI2)*6.72% -> 259.7495 | BK2: =SUM(BH2:BJ2) -> 4125.0695 | BN2: =AR2-BM2 -> 2700.52 | BP2: =AY2-BO2 -> 1034
A3: =IF(OR(B3="正常",B3="新增"),MAX(A$1:$B2)+1,"") -> 2 | B3: 正常 | C3: 零一创造欢乐（深圳）科技有限公司 | D3: 朱安莉 | E3: 450924199705013421 | F3: 广东广州 | G3: 本地城镇 | H3: 202311 | I3: 202311 | J3: 202603 | K3: =J3 -> 202603 | L3: =K3 -> 202603 | M3: 5510 | N3: 0.16 | O3: =ROUND(M3*N3,2) -> 881.6 | P3: =M3 -> 5510 | Q3: 0.08 | R3: =ROUND(P3*Q3,2) -> 440.8 | S3: =O3+R3 -> 1322.4 | T3: 6234 | U3: 0.0685 | V3: 0 | W3: =ROUND(T3*U3,2)+V3+BW3+BY3+BZ3+CA3 -> 427.03 | X3: =T3 -> 6234 | Y3: 0.02 | Z3: 0 | AA3: =ROUND(X3*Y3,2)+Z3+BX3+CB3 -> 124.68 | AB3: =W3+AA3 -> 551.71 | AC3: 3500 | AD3: 0.008 | AE3: =ROUND(AC3*AD3,2) -> 28 | AF3: =AC3 -> 3500 | AG3: 0.002 | AH3: =ROUND(AF3*AG3,2) -> 7 | AI3: =AE3+AH3 -> 35 | AJ3: 0 | AK3: 0 | AL3: =ROUND(AJ3*AK3,2) -> 0 | AM3: 3500 | AN3: 0.004 | AO3: =ROUND(AM3*AN3,2) -> 14 | AP3: =O3+AO3+AL3+AE3+W3 -> 1350.63 | AQ3: =R3+AH3+AA3 -> 572.48 | AR3: =AP3+AQ3 -> 1923.11 | AS3: 25000 | AT3: 0.12 | AU3: =ROUND(AS3*AT3,0)+CF3 -> 3000 | AV3: =AS3 -> 25000 | AW3: =AT3 -> 0.12 | AX3: =ROUND(AV3*AW3,0)+CG3 -> 3000 | AY3: =AU3+AX3 -> 6000 | AZ3: =AR3+AY3 -> 7923.11 | BA3: 30.59 | BB3: 0 | BC3: 0 | BD3: 0 | BE3: 0 | BF3: 0 | BG3: 0 | BH3: =SUM(AZ3:BG3) -> 7953.7 | BI3: 30 | BJ3: =SUM(BH3:BI3)*6.72% -> 536.50464 | BK3: =SUM(BH3:BJ3) -> 8520.2046 | BN3: =AR3-BM3 -> 1923.11 | BP3: =AY3-BO3 -> 6000
A4: =IF(OR(B4="正常",B4="新增"),MAX(A$1:$B3)+1,"") -> 3 | B4: 正常 | C4: 零一创造欢乐（深圳）科技有限公司 | D4: 黄神辉 | E4: 331081200108162119 | F4: 上海 | G4: 外地城镇 | H4: 202401 | I4: 202401 | J4: 202603 | K4: =J4 -> 202603 | L4: =K4 -> 202603 | M4: 7460 | N4: 0.16 | O4: =ROUND(M4*N4,2) -> 1193.6 | P4: =M4 -> 7460 | Q4: 0.08 | R4: =ROUNDUP(P4*Q4,2) -> 596.8 | S4: =O4+R4 -> 1790.4 | T4: 7460 | U4: 0.09 | V4: 0 | W4: =ROUND(T4*U4,2)+V4+BW4+BY4+BZ4+CA4 -> 671.4 | X4: =T4 -> 7460 | Y4: 0.02 | Z4: 0 | AA4: =ROUNDUP(X4*Y4,2)+Z4+BX4+CB4 -> 149.2 | AB4: =W4+AA4 -> 820.6 | AC4: 7460 | AD4: 0.005 | AE4: =ROUND(AC4*AD4,2) -> 37.3 | AF4: =AC4 -> 7460 | AG4: 0.005 | AH4: =ROUND(AF4*AG4,2) -> 37.3 | AI4: =AE4+AH4 -> 74.6 | AJ4: 0 | AK4: 0 | AL4: =ROUND(AJ4*AK4,2) -> 0 | AM4: 7460 | AN4: 0.002 | AO4: =ROUND(AM4*AN4,2) -> 14.92 | AP4: =O4+AO4+AL4+AE4+W4 -> 1917.22 | AQ4: =R4+AH4+AA4 -> 783.3 | AR4: =AP4+AQ4 -> 2700.52 | AS4: 7384 | AT4: 0.07 | AU4: =ROUND(AS4*AT4,0)+CF4 -> 517 | AV4: =AS4 -> 7384 | AW4: =AT4 -> 0.07 | AX4: =ROUND(AV4*AW4,0)+CG4 -> 517 | AY4: =AU4+AX4 -> 1034 | AZ4: =AR4+AY4 -> 3734.52 | BA4: =ROUNDUP(M4*1.5%*90%,1) -> 100.8 | BB4: 0 | BC4: 0 | BD4: 0 | BE4: 0 | BF4: 0 | BG4: 0 | BH4: =SUM(AZ4:BG4) -> 3835.32 | BI4: 30 | BJ4: =SUM(BH4:BI4)*6.72% -> 259.7495 | BK4: =SUM(BH4:BJ4) -> 4125.0695 | BN4: =AR4-BM4 -> 2700.52 | BP4: =AY4-BO4 -> 1034
A5: =IF(OR(B5="正常",B5="新增"),MAX(A$1:$B4)+1,"") -> 4 | B5: 正常 | C5: 零一创造欢乐（深圳）科技有限公司 | D5: 宗迪华 | E5: 310102199101191216 | F5: 上海 | G5: 本地城镇 | H5: 202403 | I5: 202403 | J5: 202603 | K5: =J5 -> 202603 | L5: =K5 -> 202603 | M5: 7460 | N5: 0.16 | O5: =ROUND(M5*N5,2) -> 1193.6 | P5: =M5 -> 7460 | Q5: 0.08 | R5: =ROUNDUP(P5*Q5,2) -> 596.8 | S5: =O5+R5 -> 1790.4 | T5: 7460 | U5: 0.09 | V5: 0 | W5: =ROUND(T5*U5,2)+V5+BW5+BY5+BZ5+CA5 -> 671.4 | X5: =T5 -> 7460 | Y5: 0.02 | Z5: 0 | AA5: =ROUNDUP(X5*Y5,2)+Z5+BX5+CB5 -> 149.2 | AB5: =W5+AA5 -> 820.6 | AC5: 7460 | AD5: 0.005 | AE5: =ROUND(AC5*AD5,2) -> 37.3 | AF5: =AC5 -> 7460 | AG5: 0.005 | AH5: =ROUND(AF5*AG5,2) -> 37.3 | AI5: =AE5+AH5 -> 74.6 | AJ5: 0 | AK5: 0 | AL5: =ROUND(AJ5*AK5,2) -> 0 | AM5: 7460 | AN5: 0.002 | AO5: =ROUND(AM5*AN5,2) -> 14.92 | AP5: =O5+AO5+AL5+AE5+W5 -> 1917.22 | AQ5: =R5+AH5+AA5 -> 783.3 | AR5: =AP5+AQ5 -> 2700.52 | AS5: 7384 | AT5: 0.07 | AU5: =ROUND(AS5*AT5,0)+CF5 -> 517 | AV5: =AS5 -> 7384 | AW5: =AT5 -> 0.07 | AX5: =ROUND(AV5*AW5,0)+CG5 -> 517 | AY5: =AU5+AX5 -> 1034 | AZ5: =AR5+AY5 -> 3734.52 | BA5: =ROUNDUP(M5*1.5%*90%,1) -> 100.8 | BB5: 0 | BC5: 0 | BD5: 0 | BE5: 0 | BF5: 0 | BG5: 0 | BH5: =SUM(AZ5:BG5) -> 3835.32 | BI5: 30 | BJ5: =SUM(BH5:BI5)*6.72% -> 259.7495 | BK5: =SUM(BH5:BJ5) -> 4125.0695 | BN5: =AR5-BM5 -> 2700.52 | BP5: =AY5-BO5 -> 1034
A6: =IF(OR(B6="正常",B6="新增"),MAX(A$1:$B5)+1,"") -> 5 | B6: 正常 | C6: 零一创造欢乐（深圳）科技有限公司 | D6: 周安洁 | E6: 34262319990821194X | F6: 上海 | G6: 外地农村 | H6: 202405 | I6: 202405 | J6: 202603 | K6: =J6 -> 202603 | L6: =K6 -> 202603 | M6: 7460 | N6: 0.16 | O6: =ROUND(M6*N6,2) -> 1193.6 | P6: =M6 -> 7460 | Q6: 0.08 | R6: =ROUNDUP(P6*Q6,2) -> 596.8 | S6: =O6+R6 -> 1790.4 | T6: 7460 | U6: 0.09 | V6: 0 | W6: =ROUND(T6*U6,2)+V6+BW6+BY6+BZ6+CA6 -> 671.4 | X6: =T6 -> 7460 | Y6: 0.02 | Z6: 0 | AA6: =ROUNDUP(X6*Y6,2)+Z6+BX6+CB6 -> 149.2 | AB6: =W6+AA6 -> 820.6 | AC6: 7460 | AD6: 0.005 | AE6: =ROUND(AC6*AD6,2) -> 37.3 | AF6: =AC6 -> 7460 | AG6: 0.005 | AH6: =ROUND(AF6*AG6,2) -> 37.3 | AI6: =AE6+AH6 -> 74.6 | AJ6: 0 | AK6: 0 | AL6: =ROUND(AJ6*AK6,2) -> 0 | AM6: 7460 | AN6: 0.002 | AO6: =ROUND(AM6*AN6,2) -> 14.92 | AP6: =O6+AO6+AL6+AE6+W6 -> 1917.22 | AQ6: =R6+AH6+AA6 -> 783.3 | AR6: =AP6+AQ6 -> 2700.52 | AS6: 7384 | AT6: 0.07 | AU6: =ROUND(AS6*AT6,0)+CF6 -> 517 | AV6: =AS6 -> 7384 | AW6: =AT6 -> 0.07 | AX6: =ROUND(AV6*AW6,0)+CG6 -> 517 | AY6: =AU6+AX6 -> 1034 | AZ6: =AR6+AY6 -> 3734.52 | BA6: =ROUNDUP(M6*1.5%*90%,1) -> 100.8 | BB6: 0 | BC6: 0 | BD6: 0 | BE6: 0 | BF6: 0 | BG6: 0 | BH6: =SUM(AZ6:BG6) -> 3835.32 | BI6: 30 | BJ6: =SUM(BH6:BI6)*6.72% -> 259.7495 | BK6: =SUM(BH6:BJ6) -> 4125.0695 | BN6: =AR6-BM6 -> 2700.52 | BP6: =AY6-BO6 -> 1034
A7: =IF(OR(B7="正常",B7="新增"),MAX(A$1:$B6)+1,"") -> 6 | B7: 正常 | C7: 零一创造欢乐（深圳）科技有限公司 | D7: 尹璐 | E7: 340503199210170020 | F7: 上海 | G7: 本地城镇 | H7: 202409 | I7: 202409 | J7: 202603 | K7: =J7 -> 202603 | L7: =K7 -> 202603 | M7: 12000 | N7: 0.16 | O7: =ROUND(M7*N7,2) -> 1920 | P7: =M7 -> 12000 | Q7: 0.08 | R7: =ROUNDUP(P7*Q7,2) -> 960 | S7: =O7+R7 -> 2880 | T7: 12000 | U7: 0.09 | V7: 0 | W7: =ROUND(T7*U7,2)+V7+BW7+BY7+BZ7+CA7 -> 1080 | X7: =T7 -> 12000 | Y7: 0.02 | Z7: 0 | AA7: =ROUNDUP(X7*Y7,2)+Z7+BX7+CB7 -> 240 | AB7: =W7+AA7 -> 1320 | AC7: 12000 | AD7: 0.005 | AE7: =ROUND(AC7*AD7,2) -> 60 | AF7: =AC7 -> 12000 | AG7: 0.005 | AH7: =ROUND(AF7*AG7,2) -> 60 | AI7: =AE7+AH7 -> 120 | AJ7: 0 | AK7: 0 | AL7: =ROUND(AJ7*AK7,2) -> 0 | AM7: 12000 | AN7: 0.002 | AO7: =ROUND(AM7*AN7,2) -> 24 | AP7: =O7+AO7+AL7+AE7+W7 -> 3084 | AQ7: =R7+AH7+AA7 -> 1260 | AR7: =AP7+AQ7 -> 4344 | AS7: 12000 | AT7: 0.07 | AU7: =ROUND(AS7*AT7,0)+CF7 -> 840 | AV7: =AS7 -> 12000 | AW7: =AT7 -> 0.07 | AX7: =ROUND(AV7*AW7,0)+CG7 -> 840 | AY7: =AU7+AX7 -> 1680 | AZ7: =AR7+AY7 -> 6024 | BA7: =ROUNDUP(M7*1.5%*90%,1) -> 162 | BB7: 0 | BC7: 0 | BD7: 0 | BE7: 0 | BF7: 0 | BG7: 0 | BH7: =SUM(AZ7:BG7) -> 6186 | BI7: 30 | BJ7: =SUM(BH7:BI7)*6.72% -> 417.7152 | BK7: =SUM(BH7:BJ7) -> 6633.7152 | BN7: =AR7-BM7 -> 4344 | BP7: =AY7-BO7 -> 1680
A8: =IF(OR(B8="正常",B8="新增"),MAX(A$1:$B7)+1,"") -> 7 | B8: 正常 | C8: 零一创造欢乐（深圳）科技有限公司 | D8: 刘慧勤 | E8: 310115198907172222 | F8: 上海 | G8: 本地城镇 | H8: 202503 | I8: 202503 | J8: 202603 | K8: =J8 -> 202603 | L8: =K8 -> 202603 | M8: 7460 | N8: 0.16 | O8: =ROUND(M8*N8,2) -> 1193.6 | P8: =M8 -> 7460 | Q8: 0.08 | R8: =ROUNDUP(P8*Q8,2) -> 596.8 | S8: =O8+R8 -> 1790.4 | T8: 7460 | U8: 0.09 | V8: 0 | W8: =ROUND(T8*U8,2)+V8+BW8+BY8+BZ8+CA8 -> 671.4 | X8: =T8 -> 7460 | Y8: 0.02 | Z8: 0 | AA8: =ROUNDUP(X8*Y8,2)+Z8+BX8+CB8 -> 149.2 | AB8: =W8+AA8 -> 820.6 | AC8: 7460 | AD8: 0.005 | AE8: =ROUND(AC8*AD8,2) -> 37.3 | AF8: =AC8 -> 7460 | AG8: 0.005 | AH8: =ROUND(AF8*AG8,2) -> 37.3 | AI8: =AE8+AH8 -> 74.6 | AJ8: 0 | AK8: 0 | AL8: =ROUND(AJ8*AK8,2) -> 0 | AM8: 7460 | AN8: 0.002 | AO8: =ROUND(AM8*AN8,2) -> 14.92 | AP8: =O8+AO8+AL8+AE8+W8 -> 1917.22 | AQ8: =R8+AH8+AA8 -> 783.3 | AR8: =AP8+AQ8 -> 2700.52 | AS8: 7384 | AT8: 0.07 | AU8: =ROUND(AS8*AT8,0)+CF8 -> 517 | AV8: =AS8 -> 7384 | AW8: =AT8 -> 0.07 | AX8: =ROUND(AV8*AW8,0)+CG8 -> 517 | AY8: =AU8+AX8 -> 1034 | AZ8: =AR8+AY8 -> 3734.52 | BA8: =ROUNDUP(M8*1.5%*90%,1) -> 100.8 | BB8: 0 | BC8: 0 | BD8: 0 | BE8: 0 | BF8: 0 | BG8: 0 | BH8: =SUM(AZ8:BG8) -> 3835.32 | BI8: 30 | BJ8: =SUM(BH8:BI8)*6.72% -> 259.7495 | BK8: =SUM(BH8:BJ8) -> 4125.0695 | BN8: =AR8-BM8 -> 2700.52 | BP8: =AY8-BO8 -> 1034
A9: =IF(OR(B9="正常",B9="新增"),MAX(A$1:$B8)+1,"") -> 8 | B9: 正常 | C9: 零一创造欢乐（深圳）科技有限公司 | D9: 陈玲 | E9: 330722199605200827 | F9: 上海 | G9: 外地农村 | H9: 202504 | I9: 202504 | J9: 202603 | K9: =J9 -> 202603 | L9: =K9 -> 202603 | M9: 25000 | N9: 0.16 | O9: =ROUND(M9*N9,2) -> 4000 | P9: =M9 -> 25000 | Q9: 0.08 | R9: =ROUNDUP(P9*Q9,2) -> 2000 | S9: =O9+R9 -> 6000 | T9: 25000 | U9: 0.09 | V9: 0 | W9: =ROUND(T9*U9,2)+V9+BW9+BY9+BZ9+CA9 -> 2250 | X9: =T9 -> 25000 | Y9: 0.02 | Z9: 0 | AA9: =ROUNDUP(X9*Y9,2)+Z9+BX9+CB9 -> 500 | AB9: =W9+AA9 -> 2750 | AC9: 25000 | AD9: 0.005 | AE9: =ROUND(AC9*AD9,2) -> 125 | AF9: =AC9 -> 25000 | AG9: 0.005 | AH9: =ROUND(AF9*AG9,2) -> 125 | AI9: =AE9+AH9 -> 250 | AJ9: 0 | AK9: 0 | AL9: =ROUND(AJ9*AK9,2) -> 0 | AM9: 25000 | AN9: 0.002 | AO9: =ROUND(AM9*AN9,2) -> 50 | AP9: =O9+AO9+AL9+AE9+W9 -> 6425 | AQ9: =R9+AH9+AA9 -> 2625 | AR9: =AP9+AQ9 -> 9050 | AS9: 25000 | AT9: 0.07 | AU9: =ROUND(AS9*AT9,0)+CF9 -> 1750 | AV9: =AS9 -> 25000 | AW9: =AT9 -> 0.07 | AX9: =ROUND(AV9*AW9,0)+CG9 -> 1750 | AY9: =AU9+AX9 -> 3500 | AZ9: =AR9+AY9 -> 12550 | BA9: =ROUNDUP(24614*1.5%*90%,1) -> 332.3 | BB9: 0 | BC9: 0 | BD9: 0 | BE9: 0 | BF9: 0 | BG9: 0 | BH9: =SUM(AZ9:BG9) -> 12882.3 | BI9: 30 | BJ9: =SUM(BH9:BI9)*6.72% -> 867.70656 | BK9: =SUM(BH9:BJ9) -> 13780.007 | BN9: =AR9-BM9 -> 9050 | BP9: =AY9-BO9 -> 3500
A10: =IF(OR(B10="正常",B10="新增"),MAX(A$1:$B9)+1,"") -> 9 | B10: 正常 | C10: 零一创造欢乐（深圳）科技有限公司 | D10: 鲁冰慧 | E10: 412728199908053166 | F10: 上海 | G10: 外地农村 | H10: 202506 | I10: 202506 | J10: 202603 | K10: =J10 -> 202603 | L10: =K10 -> 202603 | M10: 7460 | N10: 0.16 | O10: =ROUND(M10*N10,2) -> 1193.6 | P10: =M10 -> 7460 | Q10: 0.08 | R10: =ROUNDUP(P10*Q10,2) -> 596.8 | S10: =O10+R10 -> 1790.4 | T10: 7460 | U10: 0.09 | V10: 0 | W10: =ROUND(T10*U10,2)+V10+BW10+BY10+BZ10+CA10 -> 671.4 | X10: =T10 -> 7460 | Y10: 0.02 | Z10: 0 | AA10: =ROUNDUP(X10*Y10,2)+Z10+BX10+CB10 -> 149.2 | AB10: =W10+AA10 -> 820.6 | AC10: 7460 | AD10: 0.005 | AE10: =ROUND(AC10*AD10,2) -> 37.3 | AF10: =AC10 -> 7460 | AG10: 0.005 | AH10: =ROUND(AF10*AG10,2) -> 37.3 | AI10: =AE10+AH10 -> 74.6 | AJ10: 0 | AK10: 0 | AL10: =ROUND(AJ10*AK10,2) -> 0 | AM10: 7460 | AN10: 0.002 | AO10: =ROUND(AM10*AN10,2) -> 14.92 | AP10: =O10+AO10+AL10+AE10+W10 -> 1917.22 | AQ10: =R10+AH10+AA10 -> 783.3 | AR10: =AP10+AQ10 -> 2700.52 | AS10: 7384 | AT10: 0.07 | AU10: =ROUND(AS10*AT10,0)+CF10 -> 517 | AV10: =AS10 -> 7384 | AW10: =AT10 -> 0.07 | AX10: =ROUND(AV10*AW10,0)+CG10 -> 517 | AY10: =AU10+AX10 -> 1034 | AZ10: =AR10+AY10 -> 3734.52 | BA10: =ROUNDUP(M10*1.5%*90%,1) -> 100.8 | BB10: 0 | BC10: 0 | BD10: 0 | BE10: 0 | BF10: 0 | BG10: 0 | BH10: =SUM(AZ10:BG10) -> 3835.32 | BI10: 30 | BJ10: =SUM(BH10:BI10)*6.72% -> 259.7495 | BK10: =SUM(BH10:BJ10) -> 4125.0695 | BN10: =AR10-BM10 -> 2700.52 | BP10: =AY10-BO10 -> 1034
A11: =IF(OR(B11="正常",B11="新增"),MAX(A$1:$B10)+1,"") -> 10 | B11: 正常 | C11: 零一创造欢乐（深圳）科技有限公司 | D11: 李雪琪 | E11: 622725200210312627 | F11: 上海 | G11: 外地城镇 | H11: 202509 | I11: 202509 | J11: 202603 | K11: =J11 -> 202603 | L11: =K11 -> 202603 | M11: 7460 | N11: 0.16 | O11: =ROUND(M11*N11,2) -> 1193.6 | P11: =M11 -> 7460 | Q11: 0.08 | R11: =ROUNDUP(P11*Q11,2) -> 596.8 | S11: =O11+R11 -> 1790.4 | T11: 7460 | U11: 0.09 | V11: 0 | W11: =ROUND(T11*U11,2)+V11+BW11+BY11+BZ11+CA11 -> 671.4 | X11: =T11 -> 7460 | Y11: 0.02 | Z11: 0 | AA11: =ROUNDUP(X11*Y11,2)+Z11+BX11+CB11 -> 149.2 | AB11: =W11+AA11 -> 820.6 | AC11: 7460 | AD11: 0.005 | AE11: =ROUND(AC11*AD11,2) -> 37.3 | AF11: =AC11 -> 7460 | AG11: 0.005 | AH11: =ROUND(AF11*AG11,2) -> 37.3 | AI11: =AE11+AH11 -> 74.6 | AJ11: 0 | AK11: 0 | AL11: =ROUND(AJ11*AK11,2) -> 0 | AM11: 7460 | AN11: 0.002 | AO11: =ROUND(AM11*AN11,2) -> 14.92 | AP11: =O11+AO11+AL11+AE11+W11 -> 1917.22 | AQ11: =R11+AH11+AA11 -> 783.3 | AR11: =AP11+AQ11 -> 2700.52 | AS11: 7384 | AT11: 0.07 | AU11: =ROUND(AS11*AT11,0)+CF11 -> 517 | AV11: =AS11 -> 7384 | AW11: =AT11 -> 0.07 | AX11: =ROUND(AV11*AW11,0)+CG11 -> 517 | AY11: =AU11+AX11 -> 1034 | AZ11: =AR11+AY11 -> 3734.52 | BA11: =ROUNDUP(M11*1.5%*90%,1) -> 100.8 | BB11: 0 | BC11: 0 | BD11: 0 | BE11: 0 | BF11: 0 | BG11: 0 | BH11: =SUM(AZ11:BG11) -> 3835.32 | BI11: 30 | BJ11: =SUM(BH11:BI11)*6.72% -> 259.7495 | BK11: =SUM(BH11:BJ11) -> 4125.0695 | BN11: =AR11-BM11 -> 2700.52 | BP11: =AY11-BO11 -> 1034
A12: =IF(OR(B12="正常",B12="新增"),MAX(A$1:$B11)+1,"") -> 11 | B12: 正常 | C12: 零一创造欢乐（深圳）科技有限公司 | D12: 黄源畅 | E12: 460108200303112623 | F12: 上海 | G12: 外地城镇 | H12: 202509 | I12: 202509 | J12: 202603 | K12: =J12 -> 202603 | L12: =K12 -> 202603 | M12: 7460 | N12: 0.16 | O12: =ROUND(M12*N12,2) -> 1193.6 | P12: =M12 -> 7460 | Q12: 0.08 | R12: =ROUNDUP(P12*Q12,2) -> 596.8 | S12: =O12+R12 -> 1790.4 | T12: 7460 | U12: 0.09 | V12: 0 | W12: =ROUND(T12*U12,2)+V12+BW12+BY12+BZ12+CA12 -> 671.4 | X12: =T12 -> 7460 | Y12: 0.02 | Z12: 0 | AA12: =ROUNDUP(X12*Y12,2)+Z12+BX12+CB12 -> 149.2 | AB12: =W12+AA12 -> 820.6 | AC12: 7460 | AD12: 0.005 | AE12: =ROUND(AC12*AD12,2) -> 37.3 | AF12: =AC12 -> 7460 | AG12: 0.005 | AH12: =ROUND(AF12*AG12,2) -> 37.3 | AI12: =AE12+AH12 -> 74.6 | AJ12: 0 | AK12: 0 | AL12: =ROUND(AJ12*AK12,2) -> 0 | AM12: 7460 | AN12: 0.002 | AO12: =ROUND(AM12*AN12,2) -> 14.92 | AP12: =O12+AO12+AL12+AE12+W12 -> 1917.22 | AQ12: =R12+AH12+AA12 -> 783.3 | AR12: =AP12+AQ12 -> 2700.52 | AS12: 7384 | AT12: 0.07 | AU12: =ROUND(AS12*AT12,0)+CF12 -> 517 | AV12: =AS12 -> 7384 | AW12: =AT12 -> 0.07 | AX12: =ROUND(AV12*AW12,0)+CG12 -> 517 | AY12: =AU12+AX12 -> 1034 | AZ12: =AR12+AY12 -> 3734.52 | BA12: =ROUNDUP(M12*1.5%*90%,1) -> 100.8 | BB12: 0 | BC12: 0 | BD12: 0 | BE12: 0 | BF12: 0 | BG12: 0 | BH12: =SUM(AZ12:BG12) -> 3835.32 | BI12: 30 | BJ12: =SUM(BH12:BI12)*6.72% -> 259.7495 | BK12: =SUM(BH12:BJ12) -> 4125.0695 | BN12: =AR12-BM12 -> 2700.52 | BP12: =AY12-BO12 -> 1034
A13: =IF(OR(B13="正常",B13="新增"),MAX(A$1:$B12)+1,"") -> 12 | B13: 正常 | C13: 零一创造欢乐（深圳）科技有限公司 | D13: 翟萃颖 | E13: 410727200203262627 | F13: 上海 | G13: 外地农村 | H13: 202510 | I13: 202510 | J13: 202603 | K13: =J13 -> 202603 | L13: =K13 -> 202603 | M13: 7460 | N13: 0.16 | O13: =ROUND(M13*N13,2) -> 1193.6 | P13: =M13 -> 7460 | Q13: 0.08 | R13: =ROUNDUP(P13*Q13,2) -> 596.8 | S13: =O13+R13 -> 1790.4 | T13: 7460 | U13: 0.09 | V13: 0 | W13: =ROUND(T13*U13,2)+V13+BW13+BY13+BZ13+CA13 -> 671.4 | X13: =T13 -> 7460 | Y13: 0.02 | Z13: 0 | AA13: =ROUNDUP(X13*Y13,2)+Z13+BX13+CB13 -> 149.2 | AB13: =W13+AA13 -> 820.6 | AC13: 7460 | AD13: 0.005 | AE13: =ROUND(AC13*AD13,2) -> 37.3 | AF13: =AC13 -> 7460 | AG13: 0.005 | AH13: =ROUND(AF13*AG13,2) -> 37.3 | AI13: =AE13+AH13 -> 74.6 | AJ13: 0 | AK13: 0 | AL13: =ROUND(AJ13*AK13,2) -> 0 | AM13: 7460 | AN13: 0.002 | AO13: =ROUND(AM13*AN13,2) -> 14.92 | AP13: =O13+AO13+AL13+AE13+W13 -> 1917.22 | AQ13: =R13+AH13+AA13 -> 783.3 | AR13: =AP13+AQ13 -> 2700.52 | AS13: 7460 | AT13: 0.07 | AU13: =ROUND(AS13*AT13,0)+CF13 -> 522 | AV13: =AS13 -> 7460 | AW13: =AT13 -> 0.07 | AX13: =ROUND(AV13*AW13,0)+CG13 -> 522 | AY13: =AU13+AX13 -> 1044 | AZ13: =AR13+AY13 -> 3744.52 | BA13: =ROUNDUP(M13*1.5%*90%,1) -> 100.8 | BB13: 0 | BC13: 0 | BD13: 0 | BE13: 0 | BF13: 0 | BG13: 0 | BH13: =SUM(AZ13:BG13) -> 3845.32 | BI13: 30 | BJ13: =SUM(BH13:BI13)*6.72% -> 260.4215 | BK13: =SUM(BH13:BJ13) -> 4135.7415 | BN13: =AR13-BM13 -> 2700.52 | BP13: =AY13-BO13 -> 1044
A14: =IF(OR(B14="正常",B14="新增"),MAX(A$1:$B13)+1,"") -> 13 | B14: 新增 | C14: 零一创造欢乐（深圳）科技有限公司 | D14: 罗义璇 | E14: 511023199312180028 | F14: 上海 | G14: 本地城镇 | H14: 202603 | I14: 202603 | J14: 202603 | K14: =J14 -> 202603 | L14: =K14 -> 202603 | M14: 7460 | N14: 0.16 | O14: =ROUND(M14*N14,2) -> 1193.6 | P14: =M14 -> 7460 | Q14: 0.08 | R14: =ROUNDUP(P14*Q14,2) -> 596.8 | S14: =O14+R14 -> 1790.4 | T14: 7460 | U14: 0.09 | V14: 0 | W14: =ROUND(T14*U14,2)+V14+BW14+BY14+BZ14+CA14 -> 671.4 | X14: =T14 -> 7460 | Y14: 0.02 | Z14: 0 | AA14: =ROUNDUP(X14*Y14,2)+Z14+BX14+CB14 -> 149.2 | AB14: =W14+AA14 -> 820.6 | AC14: 7460 | AD14: 0.005 | AE14: =ROUND(AC14*AD14,2) -> 37.3 | AF14: =AC14 -> 7460 | AG14: 0.005 | AH14: =ROUND(AF14*AG14,2) -> 37.3 | AI14: =AE14+AH14 -> 74.6 | AJ14: 0 | AK14: 0 | AL14: =ROUND(AJ14*AK14,2) -> 0 | AM14: 7460 | AN14: 0.002 | AO14: =ROUND(AM14*AN14,2) -> 14.92 | AP14: =O14+AO14+AL14+AE14+W14 -> 1917.22 | AQ14: =R14+AH14+AA14 -> 783.3 | AR14: =AP14+AQ14 -> 2700.52 | AS14: 7460 | AT14: 0.07 | AU14: =ROUND(AS14*AT14,0)+CF14 -> 522 | AV14: =AS14 -> 7460 | AW14: =AT14 -> 0.07 | AX14: =ROUND(AV14*AW14,0)+CG14 -> 522 | AY14: =AU14+AX14 -> 1044 | AZ14: =AR14+AY14 -> 3744.52 | BA14: =ROUNDUP(M14*1.5%*90%,1) -> 100.8 | BB14: 0 | BC14: 0 | BD14: 0 | BE14: 0 | BF14: 0 | BG14: 0 | BH14: =SUM(AZ14:BG14) -> 3845.32 | BI14: 30 | BJ14: =SUM(BH14:BI14)*6.72% -> 260.4215 | BK14: =SUM(BH14:BJ14) -> 4135.7415
B15: 补收 | F15: 上海 | J15: 202602 | BJ15: =76077.18*6.72% -> 5112.3865 | BK15: =SUM(BH15:BJ15) -> 5112.3865 | BL15: 补收2月账单的全额税费
B16: 补收 | F16: 上海 | J16: 202601 | BJ16: =102240.12*6.72% -> 6870.5361 | BK16: =SUM(BH16:BJ16) -> 6870.5361 | BL16: 补收1月账单的全额税费
A18: 合计 | O18: =SUM(O2:O17) -> 18737.6 | R18: =SUM(R2:R17) -> 9368.8 | S18: =SUM(S2:S17) -> 28106.4 | V18: =SUM(V2:V17) -> 0 | W18: =SUM(W2:W17) -> 10471.03 | Z18: =SUM(Z2:Z17) -> 0 | AA18: =SUM(AA2:AA17) -> 2356.68 | AB18: =SUM(AB2:AB17) -> 12827.71 | AE18: =SUM(AE2:AE17) -> 586 | AF18: =SUM(AF2:AF17) -> 115100 | AH18: =SUM(AH2:AH17) -> 565 | AI18: =SUM(AI2:AI17) -> 1151 | AL18: =SUM(AL2:AL17) -> 0 | AO18: =SUM(AO2:AO17) -> 237.2 | AP18: =SUM(AP2:AP17) -> 30031.83 | AQ18: =SUM(AQ2:AQ17) -> 12290.48 | AR18: =SUM(AR2:AR17) -> 42322.31 | AS18: =SUM(AS2:AS17) -> 135992 | AT18: =SUM(AT2:AT17) -> 0.96 | AU18: =SUM(AU2:AU17) -> 10770 | AV18: =SUM(AV2:AV17) -> 135992 | ... BK18: =SUM(BK2:BK17) -> 82188.888 | BN18: =SUM(BN2:BN17) -> 39621.79 | BW18: =SUM(#REF!) -> #REF! | BX18: =SUM(#REF!) -> #REF! | BY18: =SUM(#REF!) -> #REF! | BZ18: =SUM(#REF!) -> #REF! | CA18: =SUM(#REF!) -> #REF! | CB18: =SUM(#REF!) -> #REF! | CF18: =SUM(#REF!) -> #REF! | CG18: =SUM(#REF!) -> #REF!
B21: 增员
B22: 序号 | C22: 公司全称 | D22: 姓名 | E22: 身份证号码 | F22: 缴纳地 | G22: 户籍性质 | H22: 社保起缴时间 | I22: 公积金起缴时间 | J22: 备注
B23: 1 | C23: 零一创造欢乐（深圳）科技有限公司 | D23: 罗义璇 | E23: 511023199312180028 | F23: 上海 | G23: 本地城镇 | H23: 202603 | I23: 202603
B24: 2
B25: 3
B26: 4
B27: 5
B28: 6
B29: 7
B30: 8
B31: 9
B32: 10
B33: 11
B34: 减员
B35: 序号 | C35: 公司全称 | D35: 姓名 | E35: 身份证号码 | F35: 缴纳地 | G35: 户籍性质 | H35: 社保停缴时间 | I35: 公积金停缴时间 | J35: 离职原因
B36: 1 | C36: 零一创造欢乐（深圳）科技有限公司 | D36: 韦旭峰 | E36: 310113199007222118 | F36: 上海 | G36: 本地城镇 | H36: 20260228 | I36: 20260228
B37: 2
B38: 3
B39: 4
B40: 5
B41: 5
