Workbook
Name rngAction: #REF!
Name rngBlockFactor: #REF!
Name rngCIName: #REF!
Name rngCINameHidden: #REF!
Name rngDataInputCIName: #REF!
Name rngErrorThreshold: #REF!
Name rngFileNameHidden: #REF!
Name rngHTTPPort: #REF!
Name rngLanguageCD: #REF!
Name rngMachineName: #REF!
Name rngNode: #REF!
Name rngPasswordHidden: #REF!
Name rngPortal: #REF!
Name rngProtocol: #REF!
Name rngPSSiteName: #REF!
Name rngResHeaders: #REF!
Name rngURL: #REF!
Name rngUserIDHidden: #REF!
Name rngXmlConst: #REF!
Name txtBoxTitleConnectInfo: "txtBoxTitle"
Name txtBoxTitleCreateTemplate: "txtBoxTitle"
Name txtBoxTitleInputData: "txtBoxTitle"
Name txtBoxTitleStageSubmitData: "txtBoxTitle"

Sheet 付款通知书
A2: 付款通知书
A3: 付款单位: | B3: 零一裂变（深圳）科技有限公司
A4: 账单月 | B4: 缴纳地 | C4: 社保小计 | D4: 公积金小计 | E4: 残障金小计 | F4: 其他 | G4: 服务费 | H4: 全额税费 | I4: 合计 | J4: 备注 | K4: 合作产品
A5: 202603 | B5: 上海 | C5: =SUMIF(付款明细!F:F,B5,付款明细!AR:AR) -> 5401.04 | D5: =SUMIF(付款明细!F:F,B5,付款明细!AY:AY) -> 2068 | E5: =SUMIF(付款明细!F:F,B5,付款明细!BA:BA) -> 201.6 | F5: =付款明细!BG7 -> 0 | G5: =SUMIF(付款明细!F:F,B5,付款明细!BI:BI) -> 60 | H5: =SUMIF(付款明细!F:F,B5,付款明细!BJ:BJ) -> 1558.497 | I5: =SUM(C5:H5) -> 9289.137 | J5: 2 | K5: 人事外包
A6: 历史结余
A7: 合计 | C7: =ROUND(SUM(C5:C6),2) -> 5401.04 | D7: =ROUND(SUM(D5:D6),2) -> 2068 | E7: =ROUND(SUM(E5:E6),2) -> 201.6 | F7: =ROUND(SUM(F5:F6),2) -> 0 | G7: =ROUND(SUM(G5:G6),2) -> 60 | H7: =ROUND(SUM(H5:H6),2) -> 1558.5 | I7: =ROUND(SUM(I5:I6),2) -> 9289.14 | J7: =SUM(J5:J6) -> 2
A9: 汇入公司名称：深圳市万泉河人力资源有限公司
A10: 开户行：中国银行深圳金地支行
A11: 帐 号：745857952481
A12: 社保顾问：薛小妹
A13: 联系电话：0755-33037777-885
A14: 特别说明： 1、请以零一裂变（深圳）科技有限公司公账付款至我司，我司不接受其他公司代支付，亦不接受个人账户打款。 2、请在首次款项支付当月向我司顾问提供准确的开票信息，逾期不予开具发票；次月起，发票类型、发票税号、发票寄送信息等相关开票信息如有变更，请在当月款项支付前告知我司顾问。 3、开票抬头为：零一裂变（深圳）科技有限公司，如有疑义请在汇款前联系我司顾问，款项支付后开票抬头无法变更。

Sheet 付款明细
A1: 序号 | B1: 状态 | C1: 客户名称 | D1: 姓名 | E1: 身份证号 | F1: 参保地 | G1: 户籍性质 | H1: 社保起做时间 | I1: 公积金起做时间 | J1: 帐单年月 | K1: 社保费用所属月（缴纳月） | L1: 公积金费用所属月（缴纳月） | M1: 养老企业基数 | N1: 养老企业比例 | O1: 养老企业汇缴 | P1: 养老个人基数 | Q1: 养老个人比例 | R1: 养老个人汇缴 | S1: 养老合计 | T1: 医疗企业基数 | U1: 医疗企业比例 | V1: 医疗企业大病 | W1: 医疗企业汇缴 | X1: 医疗个人基数 | Y1: 医疗个人比例 | Z1: 医疗个人大病 | AA1: 医疗个人汇缴 | AB1: 医疗合计 | AC1: 失业企业基数 | AD1: 失业企业比例 | AE1: 失业单位汇缴 | AF1: 失业个人基数 | AG1: 失业个人比例 | AH1: 失业个人汇缴 | AI1: 失业合计 | AJ1: 生育企业基数 | AK1: 生育企业比例 | AL1: 生育企业汇缴 | AM1: 工伤企业基数 | AN1: 工伤企业比例 | AO1: 工伤企业汇缴 | AP1: 单位社保 | AQ1: 个人社保 | AR1: 社保合计 | AS1: 公积金企业基数 | AT1: 公积金企业比例 | AU1: 公积金企业汇缴 | AV1: 公积金个人基数 | AW1: 公积金个人比例 | AX1: 公积金个人汇缴 | AY1: 公积金合计 | AZ1: 社保公积金小计 | BA1: 残保金企业缴纳 | BB1: 滞纳金 | BC1: 档案费 | BD1: 制卡费 | BE1: 工会费 | BF1: 采暖费 | BG1: 其它费用 | BH1: 小计（不含服务费） | BI1: 服务费 | BJ1: 全额税费 | BK1: 合计 | BL1: 备注 | BM1: 社保 | BN1: 社保差额 | BO1: 公积金 | BP1: 公积金差额 | BQ1: 原因 | BR1: 社保编号 | BS1: 公积金编号 | BT1: 医保个账 | BU1: 住院基本医疗 | BV1: 住院补充医疗 | BW1: 门诊基本医疗 | BX1: 医保个账单位金额 | BY1: 医保个账个人金额 | BZ1: 住院基本医疗单位金额 | CA1: 住院补充医疗单位金额 | CB1: 门诊医疗单位金额 | CC1: 门诊医疗个人金额 | CD1: 补充公积金 基数 | CE1: 补充公积金 单位比例 | CF1: 补充公积金 个人比例 | CG1: 补充公积 金单位金额 | CH1: 补充公积金 个人金额
A2: =IF(OR(B2="正常",B2="新增"),MAX(A$1:$B1)+1,"") -> 1 | B2: 正常 | C2: 零一裂变（深圳）科技有限公司 | D2: 黄小雨 | E2: 430603199307073021 | F2: 上海 | G2: 外地农村 | H2: 202306 | I2: 202306 | J2: 202603 | K2: =J2 -> 202603 | L2: =K2 -> 202603 | M2: 7460 | N2: 0.16 | O2: =ROUND(M2*N2,2) -> 1193.6 | P2: =M2 -> 7460 | Q2: 0.08 | R2: =ROUND(P2*Q2,2) -> 596.8 | S2: =O2+R2 -> 1790.4 | T2: 7460 | U2: 0.09 | V2: 0 | W2: =ROUND(T2*U2,2)+V2+BX2+BZ2+CA2+CB2 -> 671.4 | X2: =T2 -> 7460 | Y2: 0.02 | Z2: 0 | AA2: =ROUND(X2*Y2,2)+Z2+BY2+CC2 -> 149.2 | AB2: =W2+AA2 -> 820.6 | AC2: 7460 | AD2: 0.005 | AE2: =ROUND(AC2*AD2,2) -> 37.3 | AF2: =AC2 -> 7460 | AG2: 0.005 | AH2: =ROUND(AF2*AG2,2) -> 37.3 | AI2: =AE2+AH2 -> 74.6 | AJ2: 7460 | AK2: 0 | AL2: =ROUND(AJ2*AK2,2) -> 0 | AM2: 7460 | AN2: 0.002 | AO2: =ROUND(AM2*AN2,2) -> 14.92 | AP2: =O2+AO2+AL2+AE2+W2 -> 1917.22 | AQ2: =R2+AH2+AA2 -> 783.3 | AR2: =AP2+AQ2 -> 2700.52 | AS2: 7384 | AT2: 0.07 | AU2: =ROUND(AS2*AT2,0)+CG2 -> 517 | AV2: =AS2 -> 7384 | AW2: =AT2 -> 0.07 | AX2: =ROUND(AV2*AW2,0)+CH2 -> 517 | AY2: =AU2+AX2 -> 1034 | AZ2: =AR2+AY2 -> 3734.52 | BA2: =ROUNDUP(M2*1.5%*90%,1) -> 100.8 | BB2: 0 | BC2: 0 | BD2: 0 | BE2: 0 | BF2: 0 | BG2: 0 | BH2: =SUM(AZ2:BG2) -> 3835.32 | BI2: 30 | BJ2: =SUM(BH2:BI2)*6.72% -> 259.7495 | BK2: =SUM(BH2:BJ2) -> 4125.0695 | BN2: =AR2-BM2 -> 2700.52 | BP2: =AY2-BO2 -> 1034
A3: =IF(OR(B3="正常",B3="新增"),MAX(A$1:$B2)+1,"") -> 2 | B3: 正常 | C3: 零一裂变（深圳）科技有限公司 | D3: 沈青漪 | E3: 310105199001152024 | F3: 上海 | G3: 本地城镇 | H3: 202307 | I3: 202307 | J3: 202603 | K3: =J3 -> 202603 | L3: =K3 -> 202603 | M3: 7460 | N3: 0.16 | O3: =ROUND(M3*N3,2) -> 1193.6 | P3: =M3 -> 7460 | Q3: 0.08 | R3: =ROUND(P3*Q3,2) -> 596.8 | S3: =O3+R3 -> 1790.4 | T3: 7460 | U3: 0.09 | V3: 0 | W3: =ROUND(T3*U3,2)+V3+BX3+BZ3+CA3+CB3 -> 671.4 | X3: =T3 -> 7460 | Y3: 0.02 | Z3: 0 | AA3: =ROUND(X3*Y3,2)+Z3+BY3+CC3 -> 149.2 | AB3: =W3+AA3 -> 820.6 | AC3: 7460 | AD3: 0.005 | AE3: =ROUND(AC3*AD3,2) -> 37.3 | AF3: =AC3 -> 7460 | AG3: 0.005 | AH3: =ROUND(AF3*AG3,2) -> 37.3 | AI3: =AE3+AH3 -> 74.6 | AJ3: 7460 | AK3: 0 | AL3: =ROUND(AJ3*AK3,2) -> 0 | AM3: 7460 | AN3: 0.002 | AO3: =ROUND(AM3*AN3,2) -> 14.92 | AP3: =O3+AO3+AL3+AE3+W3 -> 1917.22 | AQ3: =R3+AH3+AA3 -> 783.3 | AR3: =AP3+AQ3 -> 2700.52 | AS3: 7384 | AT3: 0.07 | AU3: =ROUND(AS3*AT3,0)+CG3 -> 517 | AV3: =AS3 -> 7384 | AW3: =AT3 -> 0.07 | AX3: =ROUND(AV3*AW3,0)+CH3 -> 517 | AY3: =AU3+AX3 -> 1034 | AZ3: =AR3+AY3 -> 3734.52 | BA3: =ROUNDUP(M3*1.5%*90%,1) -> 100.8 | BB3: 0 | BC3: 0 | BD3: 0 | BE3: 0 | BF3: 0 | BG3: 0 | BH3: =SUM(AZ3:BG3) -> 3835.32 | BI3: 30 | BJ3: =SUM(BH3:BI3)*6.72% -> 259.7495 | BK3: =SUM(BH3:BJ3) -> 4125.0695 | BN3: =AR3-BM3 -> 2700.52 | BP3: =AY3-BO3 -> 1034
B4: 补收 | F4: 上海 | J4: 202602 | BJ4: =7730.64*6.72% -> 519.49901 | BK4: =SUM(BH4:BJ4) -> 519.49901 | BL4: 补收2月账单的全额税费
B5: 补收 | F5: 上海 | J5: 202601 | BJ5: =7730.64*6.72% -> 519.49901 | BK5: =SUM(BH5:BJ5) -> 519.49901 | BL5: 补收1月账单的全额税费
A7: 合计 | O7: =SUM(O2:O6) -> 2387.2 | R7: =SUM(R2:R6) -> 1193.6 | S7: =SUM(S2:S6) -> 3580.8 | V7: =SUM(V2:V6) -> 0 | W7: =SUM(W2:W6) -> 1342.8 | Z7: =SUM(Z2:Z6) -> 0 | AA7: =SUM(AA2:AA6) -> 298.4 | AB7: =SUM(AB2:AB6) -> 1641.2 | AE7: =SUM(AE2:AE6) -> 74.6 | AF7: =SUM(AF2:AF6) -> 14920 | AH7: =SUM(AH2:AH6) -> 74.6 | AI7: =SUM(AI2:AI6) -> 149.2 | AL7: =SUM(AL2:AL6) -> 0 | AO7: =SUM(AO2:AO6) -> 29.84 | AP7: =SUM(AP2:AP6) -> 3834.44 | AQ7: =SUM(AQ2:AQ6) -> 1566.6 | AR7: =SUM(AR2:AR6) -> 5401.04 | AS7: =SUM(AS2:AS6) -> 14768 | AT7: =SUM(AT2:AT6) -> 0.14 | AU7: =SUM(AU2:AU6) -> 1034 | AV7: =SUM(AV2:AV6) -> 14768 | ... BK7: =SUM(BK2:BK6) -> 9289.137 | BX7: =SUM(#REF!) -> #REF! | BY7: =SUM(#REF!) -> #REF! | BZ7: =SUM(#REF!) -> #REF! | CA7: =SUM(#REF!) -> #REF! | CB7: =SUM(#REF!) -> #REF! | CC7: =SUM(#REF!) -> #REF! | CG7: =SUM(#REF!) -> #REF! | CH7: =SUM(#REF!) -> #REF!
B10: 增员
B11: 序号 | C11: 公司全称 | D11: 姓名 | E11: 身份证号码 | F11: 缴纳地 | G11: 户籍性质 | H11: 社保起缴时间 | I11: 公积金起缴时间 | J11: 备注
B12: 1
B13: 2
B14: 3
B15: 4
B16: 5
B17: 6
B18: 7
B19: 8
B20: 减员
B21: 序号 | C21: 公司全称 | D21: 姓名 | E21: 身份证号码 | F21: 缴纳地 | G21: 户籍性质 | H21: 社保停缴时间 | I21: 公积金停缴时间 | J21: 离职原因
B22: 1
B23: 2
B24: 3
B25: 4
B26: 5
B27: 6
B28: 7
B29: 8
